{
  "name": "pol-deploy-sql-tde",
  "properties": {
    "displayName": "Deploy SQL Database Transparent Data Encryption",
    "description": "Deploy the Transparent Data Encryption when it is not enabled in the deployment.",
    "metadata": {
      "category": "Application and Database security",
      "version": "2.1.0",
      "preview": false,
      "deprecated": false,
      "source_builtIn_name": "86a912f6-9a06-4e26-b447-11b16ba8659f"
    },
    "mode": "Indexed",
    "parameters": {
      "effect": {
        "type": "string",
        "metadata": {
          "displayName": "Effect",
          "description": "Enable or disable the execution of the policy"
        },
        "allowedValues": [
          "DeployIfNotExists",
          "Disabled"
        ],
        "defaultValue": "DeployIfNotExists"
      },
      "evaluationDelay": {
        "type": "string",
        "metadata": {
          "displayName": "Evaluation Delay",
          "description": "Specifies when the existence of the related resources should be evaluated. The delay is only used for evaluations that are a result of a create or update resource request. Allowed values are AfterProvisioning, AfterProvisioningSuccess, AfterProvisioningFailure, or an ISO 8601 duration between 0 and 360 minutes."
        },
        "defaultValue": "AfterProvisioning"
      }
    },
    "policyRule": {
      "if": {
        "allOf": [
          {
            "field": "type",
            "equals": "Microsoft.Sql/servers/databases"
          },
          {
            "field": "name",
            "notEquals": "master"
          }
        ]
      },
      "then": {
        "effect": "[parameters('effect')]",
        "details": {
          "type": "Microsoft.Sql/servers/databases/transparentDataEncryption",
          "evaluationDelay": "[parameters('evaluationDelay')]",
          "name": "current",
          "existenceCondition": {
            "anyOf": [
              {
                "field": "Microsoft.Sql/transparentDataEncryption.status",
                "equals": "enabled"
              },
              {
                "field": "Microsoft.Sql/servers/databases/transparentDataEncryption/state",
                "equals": "enabled"
              }
            ]
          },
          "roleDefinitionIds": [
            "/providers/microsoft.authorization/roleDefinitions/9b7fa17d-e63e-47b0-bb0a-15c516ac86ec"
          ],
          "deployment": {
            "properties": {
              "mode": "incremental",
              "template": {
                "$schema": "https://schema.management.azure.com/schemas/2015-01-01/deploymentTemplate.json#",
                "contentVersion": "1.0.0.0",
                "parameters": {
                  "fullDbName": {
                    "type": "string"
                  }
                },
                "variables": {},
                "resources": [
                  {
                    "name": "[concat(parameters('fullDbName'), '/current')]",
                    "type": "Microsoft.Sql/servers/databases/transparentDataEncryption",
                    "apiVersion": "2022-05-01-preview",
                    "properties": {
                      "state": "Enabled"
                    }
                  }
                ],
                "outputs": {}
              },
              "parameters": {
                "fullDbName": {
                  "value": "[field('fullName')]"
                }
              }
            }
          }
        }
      }
    }
  }
}
